{
  "donnes": {
    "matricule": "20_240",
    "nom": "Mounsif",
    "prenom": "Sed",
    "Datenaissance": "6/2/2002",
    "sex": "MALE",
    "motdePasse": "7e38d0573079ab7953d3dbfa0fdeda00abc3afbb56f19f32e4d6375167b4bd80",
    "Email": "Kl_Bingo1@esi.dz",
    "niveauEtude": "2CP",
    "bioPersonnel": ""
  },
  "contacts": {
    "nbTelephone": 0,
    "countFacebook": "",
    "countGithub": "",
    "countLinkedln": ""
  },
  "listProjets": [
    {
      "title": "projet4",
      "id": "40dc4840-08cb-4f84-95aa-2d19b3da7e0d",
      "type": "",
      "competences": [
        {
          "FamilledeCompetence": "CF4: Concevoir, réaliser et maintenir des logiciels de qualité",
          "Competence": "C4.0: Développer des programmes informatiques",
          "ElemdeCompetence": "C40.2: Identifier les structures algorithmiques statiques et dynamiques adéquate pour construire un algorithme à partir de l’analyse d’un problème",
          "modules": [
            "ALSDD",
            "ALSDS"
          ],
          "type": "MET",
          "ObjectifPédagogique": ""
        },
        {
          "FamilledeCompetence": "CF4: Concevoir, réaliser et maintenir des logiciels de qualité",
          "Competence": "C4.0: Développer des programmes informatiques",
          "ElemdeCompetence": "C40.4: Proposer un découpage modulaire en procédures et/ou fonctions et le justifier",
          "modules": [
            "ALSDD",
            "ALSDS"
          ],
          "type": "TEC",
          "ObjectifPédagogique": "Programmer séparément les divers algorithmes correspondants aux modules (principal et secondaires)"
        },
        {
          "FamilledeCompetence": "CF4: Concevoir, réaliser et maintenir des logiciels de qualité",
          "Competence": "C4.0: Développer des programmes informatiques",
          "ElemdeCompetence": "C40.5: Traduire un algorithme dans un langage de programmation et le commenter",
          "modules": [
            "ALSDD",
            "ALSDS",
            "PYT"
          ],
          "type": "TEC",
          "ObjectifPédagogique": "Développer des applications informatiques répondant aux besoins d\u0027un client"
        },
        {
          "FamilledeCompetence": "",
          "Competence": "",
          "ElemdeCompetence": "mon compétence",
          "modules": [
            ""
          ],
          "ObjectifPédagogique": ""
        }
      ],
      "date": "2022-05-04",
      "imgPath": "40dc4840-08cb-4f84-95aa-2d19b3da7e0d",
      "docs": [],
      "description": ""
    },
    {
      "title": "projet5",
      "id": "9b4bdb0b-77f8-415b-abb2-ebc4e4c05ecf",
      "type": "",
      "competences": [
        {
          "FamilledeCompetence": "CF4: Concevoir, réaliser et maintenir des logiciels de qualité",
          "Competence": "C4.0: Développer des programmes informatiques",
          "ElemdeCompetence": "C40.2: Identifier les structures algorithmiques statiques et dynamiques adéquate pour construire un algorithme à partir de l’analyse d’un problème",
          "modules": [
            "ALSDD",
            "ALSDS"
          ],
          "type": "MET",
          "ObjectifPédagogique": ""
        },
        {
          "FamilledeCompetence": "CF4: Concevoir, réaliser et maintenir des logiciels de qualité",
          "Competence": "C4.0: Développer des programmes informatiques",
          "ElemdeCompetence": "C40.4: Proposer un découpage modulaire en procédures et/ou fonctions et le justifier",
          "modules": [
            "ALSDD",
            "ALSDS"
          ],
          "type": "TEC",
          "ObjectifPédagogique": "Programmer séparément les divers algorithmes correspondants aux modules (principal et secondaires)"
        },
        {
          "FamilledeCompetence": "CF4: Concevoir, réaliser et maintenir des logiciels de qualité",
          "Competence": "C4.0: Développer des programmes informatiques",
          "ElemdeCompetence": "C40.5: Traduire un algorithme dans un langage de programmation et le commenter",
          "modules": [
            "ALSDD",
            "ALSDS",
            "PYT"
          ],
          "type": "TEC",
          "ObjectifPédagogique": "Développer des applications informatiques répondant aux besoins d\u0027un client"
        },
        {
          "FamilledeCompetence": "",
          "Competence": "",
          "ElemdeCompetence": "mon compétence",
          "modules": [
            ""
          ],
          "ObjectifPédagogique": ""
        }
      ],
      "date": "2022-05-04",
      "imgPath": "9b4bdb0b-77f8-415b-abb2-ebc4e4c05ecf",
      "docs": [],
      "description": "projet 2cp"
    },
    {
      "title": "",
      "id": "b0160aa9-a82d-4ec6-8bf9-f3f2f6be52a0",
      "type": "",
      "competences": [
        {
          "FamilledeCompetence": "CF4: Concevoir, réaliser et maintenir des logiciels de qualité",
          "Competence": "C4.A: Analyser et concevoir des algorithmes",
          "ElemdeCompetence": "C4A.1: Etudier les structures de données et de fichiers et analyser l’efficacité des algorithmes",
          "modules": [
            "ALSDD",
            "SFSD",
            "TPRO",
            "CRP"
          ],
          "type": "MET",
          "ObjectifPédagogique": ""
        },
        {
          "FamilledeCompetence": "CF7: Concevoir, mettre en œuvre et administrer des infrastructures complexes et réparties",
          "Competence": "C7.7: Exploiter un système d\u0027exploitation centralisé",
          "ElemdeCompetence": "C77.6: Différencier les technologies de stockage",
          "modules": [
            "SFSD"
          ],
          "type": "OPE",
          "ObjectifPédagogique": ""
        },
        {
          "FamilledeCompetence": "",
          "Competence": "",
          "ElemdeCompetence": "shvdgsgdcgscdg",
          "modules": [
            ""
          ],
          "ObjectifPédagogique": ""
        }
      ],
      "date": "2022-05-12",
      "imgPath": "b0160aa9-a82d-4ec6-8bf9-f3f2f6be52a0",
      "docs": [],
      "description": "zbhvvzvvdvzd"
    }
  ],
  "listPortfolio": []
}